LICENSE
subclean/__init__.py
subclean/blacklist.py
subclean/cli.py
subclean/core/__init__.py
subclean/core/line.py
subclean/core/parser.py
subclean/core/section/__init__.py
subclean/core/section/timing.py
subclean/core/subtitle.py
subclean/processors/__init__.py
subclean/processors/processor.py
subclean/py.typed
subclean/subclean.py
subclean-0.5.0.dist-info/entry_points.txt
subclean-0.5.0.dist-info/LICENSE
subclean-0.5.0.dist-info/WHEEL
subclean-0.5.0.dist-info/METADATA
subclean-0.5.0.dist-info/RECORD
