Metadata-Version: 2.1
Name: subclean
Version: 0.5.0
Summary: Simple CLI tool to instantly enhance your movie & TV show subtitles.
Home-page: https://github.com/disrupted/subclean
License: GPL-3.0
Keywords: subtitle,cli,media,plex
Author: disrupted
Author-email: hi@salomonpopp.me
Requires-Python: >=3.9,<4.0
Classifier: Environment :: Console
Classifier: License :: OSI Approved :: GNU General Public License v3 (GPLv3)
Classifier: Operating System :: OS Independent
Classifier: Programming Language :: Python :: 3
Classifier: Programming Language :: Python :: 3.10
Classifier: Programming Language :: Python :: 3.9
Requires-Dist: loguru (>=0.5.3,<0.6.0)
Project-URL: Issues, https://github.com/disrupted/subclean/issues
Project-URL: Repository, https://github.com/disrupted/subclean
